[
  {
    "missionId": "fd339e14-1d9f-4f61-b936-00f813d37276",
    "frequencies": [
      {
        "frequencyId": "123.700",
        "couplingAllowed": true
      },
      {
        "frequencyId": "125.500",
        "couplingAllowed": false
      }
    ]
  },
  {
    "missionId": "8b75e49e-1a23-4e13-8db9-f0563adfb55d",
    "frequencies": [
      {
        "frequencyId": "123.700",
        "couplingAllowed": true
      },
      {
        "frequencyId": "125.500",
        "couplingAllowed": false
      }
    ]
  },
  {
    "missionId": "4826ac35-ed86-4cf9-bafe-6bf6f49b3f4a",
    "frequencies": [
      {
        "frequencyId": "123.700",
        "couplingAllowed": true
      },
      {
        "frequencyId": "125.500",
        "couplingAllowed": false
      }
    ]
  }
]
