{
  "sipProxy": {
    "opSipProxyHost": "10.17.15.141",
    "opSipProxyListeningPort": 5060
  },
  "hostSpecificConfigurationMap": {
    "CWP-VST02-15": {
      "opPhysicalEntity": {
        "opSipEndpoint": {
          "opPhysicalHost": "192.168.100.148",
          "opSipListeningPort": 5060
        },
        "opSipDomain": "example.com",
        "opUserInfo": "222222",
        "opSipRegistrationTimeoutInSeconds": 64800,
        "opMaxConcurrentCallsCount": 20
      }
    },
    "CWP-VST02-16": {
      "opPhysicalEntity": {
        "opSipEndpoint": {
          "opPhysicalHost": "192.168.100.147",
          "opSipListeningPort": 5060
        },
        "opSipDomain": "example.com",
        "opUserInfo": "op3",
        "opSipRegistrationTimeoutInSeconds": 64800,
        "opMaxConcurrentCallsCount": 20
      }
    },
    "CWP-VST02-14": {
      "opPhysicalEntity": {
        "opSipEndpoint": {
          "opPhysicalHost": "192.168.100.147",
          "opSipListeningPort": 5060
        },
        "opSipDomain": "example.com",
        "opUserInfo": "111111",
        "opSipRegistrationTimeoutInSeconds": 64800,
        "opMaxConcurrentCallsCount": 20
      }
    }
  },
  "audioAppResources": {
    "audioAppPhoneResourcePoolSize": 10
  }
}
